sciencewriter/__init__.py
sciencewriter/_api.py
sciencewriter/analysisfeature.py
sciencewriter/informationmodel.py
sciencewriter/sciencewriter.py
sciencewriter/suggestionsfeature.py
sciencewriter-0.0.2.dist-info/LICENSE
sciencewriter-0.0.2.dist-info/METADATA
sciencewriter-0.0.2.dist-info/WHEEL
sciencewriter-0.0.2.dist-info/dependency_links.txt
sciencewriter-0.0.2.dist-info/top_level.txt
sciencewriter-0.0.2.dist-info/RECORD
