Metadata-Version: 2.1
Name: sciencewriter
Version: 0.0.2
Summary: A package to maintain argumentation consistency for academic writing
Home-page: https://github.com/rayniervanegmond/sciencewriter
Author: Raynier van Egmond
Author-email: raynierx@gmail.com
License: GNU General Public License v3
Keywords: sciencewriter
Platform: UNKNOWN
Classifier: Development Status :: 2 - Pre-Alpha
Classifier: Intended Audience :: Developers
Classifier: License :: OSI Approved :: GNU General Public License v3 (GPLv3)
Classifier: Natural Language :: English
Classifier: Programming Language :: Python :: 3
Classifier: Programming Language :: Python :: 3.5
Classifier: Programming Language :: Python :: 3.6
Classifier: Programming Language :: Python :: 3.7
Classifier: Programming Language :: Python :: 3.8
Requires-Python: >=3.5
Requires-Dist: pytest (==6.2.4)
